{
  "file_name": "form4.json",
  "revision_date": "2024-06-20",
  "inspection_date": "2024-07-15",
  "section_name": "УПП",
  "inspector": "Иванов А.С.",
  "sections": {
    "A": {
      "description": "Состояние рабочего пространства укладчика-упаковщика (оператора ЦП, наладчика участка производства СКПГ, дробильщика, подсобного рабочего)",
      "criteria": [
        {
          "number": 1,
          "description": "На полу отсутствует пыль, грязь. Под оборудованием и вокруг него отсутствует россыпи сырья и/или красителя, мусор, литники, продукция, пакеты из-под материала, другие предметы",
          "complies": 1,
          "does_not_comply": null,
          "comment": ""
        },
        {
          "number": 2,
          "description": "Личные вещи отсутствуют в рабочей зоне работника (на оборудовании, стуле, стойке и т.д.), в том числе спецодежда",
          "complies": 0,
          "does_not_comply": 0,
          "comment": "На стуле обнаружена личная куртка работника"
        },
        {
          "number": 3,
          "description": "На оборудовании и в рабочей зоне отсутствуют посторонние предметы, непредназначенные для выполнения профессиональных обязанностей",
          "complies": 1,
          "does_not_comply": null,
          "comment": ""
        },
        {
          "number": 4,
          "description": "Уборочный инвентарь имеется в наличии и размещен аккуратно в установленном месте",
          "complies": 0,
          "does_not_comply": 0,
          "comment": "Ведро и швабра оставлены в проходе, не на своем месте"
        },
        {
          "number": 5,
          "description": "Тара, упаковочные материалы, поддоны, готовая продукция, несоответствующая продукция размещены в зонах разметки",
          "complies": 1,
          "does_not_comply": null,
          "comment": ""
        },
        {
          "number": 6,
          "description": "Проходы вокруг оборудования свободные и нет загромождений продукцией, тарой, поддонами и другими предметами",
          "complies": 0,
          "does_not_comply": 0,
          "comment": "Поддоны с продукцией частично перекрывают проход к станку №3"
        }
      ],
      "subdivisions": {}
    },
    "B": {
      "description": "Состояние оборудования",
      "criteria": [],
      "subdivisions": {
        "B1": {
          "description": "Ответственность наладчика производственного участка",
          "criteria": [
            {
              "number": 1,
              "description": "Отсутствие пыли и грязи на оборудовании (станине, конвейерной ленте, шлангах и других элементах оборудования) 1",
              "complies": 0,
              "does_not_comply": 0,
              "comment": "На станине станка №5 скопилась пыль и остатки материала"
            },
            {
              "number": 2,
              "description": "Тумбочки и шкафы с инструментами наладчиков идентифицированы и чистые.",
              "complies": 1,
              "does_not_comply": null,
              "comment": ""
            },
            {
              "number": 3,
              "description": "На оборудовании имеются все защитные экраны.",
              "complies": 1,
              "does_not_comply": null,
              "comment": ""
            },
            {
              "number": 4,
              "description": "На оборудовании отсутствуют крепления скотчем, картона на конвейерной ленте и других элементах оборудования",
              "complies": 0,
              "does_not_comply": 0,
              "comment": "На конвейерной ленте станка №2 закреплен картон скотчем"
            },
            {
              "number": 5,
              "description": "Внутри оборудования отсутствуют посторонние предметы, в том числе остатки продукции от прошлых производственных партий и текущей производственной партии.",
              "complies": 1,
              "does_not_comply": null,
              "comment": ""
            },
            {
              "number": 6,
              "description": "Технологическая оснастка (пресс-формы) хранятся в специально отведенных местах.",
              "complies": 0,
              "does_not_comply": 0,
              "comment": "2 пресс-формы оставлены на полу возле станка №4"
            }
          ]
        },
        "B2": {
          "description": "Ответственность персонала ЭМО",
          "criteria": [
            {
              "number": 1,
              "description": "Течь масла, охлаждающих жидкостей с оборудования отсутствует. Пол около оборудования чистый и сухой",
              "complies": 0,
              "does_not_comply": 0,
              "comment": "Под станком №3 обнаружены следы масла"
            },
            {
              "number": 2,
              "description": "Внутри оборудования все элементы (провода, шланги, и др.) закреплены монтажными стяжками (применение скотча, целлофана, ленточек, ветоши и др. посторонних предметов исключено).",
              "complies": 1,
              "does_not_comply": null,
              "comment": ""
            },
            {
              "number": 3,
              "description": "На технологическом оборудовании и других видах оборудования, применяемых на участке, отсутствуют повреждения изоляции электропроводки, лакокрасочных покрытий и т.д.",
              "complies": 0,
              "does_not_comply": 0,
              "comment": "На панели управления станка №1 повреждено лакокрасочное покрытие"
            },
            {
              "number": 4,
              "description": "Отсутствуют вещи, оставленные после работы вспомогательных служб на производственном участке",
              "complies": 1,
              "does_not_comply": null,
              "comment": ""
            },
            {
              "number": 5,
              "description": "Панель управления в технически исправном состоянии, все надписи читаемы, видимые повреждения отсутствуют",
              "complies": 1,
              "does_not_comply": null,
              "comment": ""
            },
            {
              "number": 6,
              "description": "На оборудовании имеются все защитные ограждения, предусмотренные конструкцией оборудования, в том числе закрывающие подвижные механизмы.",
              "complies": 0,
              "does_not_comply": 0,
              "comment": "На станке №6 отсутствует защитное ограждение конвейерной ленты"
            }
          ]
        }
      }
    },
    "C": {
      "description": "Состояние производственного участка и вспомогательных помещений (кладовых, складов)",
      "criteria": [
        {
          "number": 1,
          "description": "Пол, подоконники, колонны, стены, двери чистые (нет пыли, грязи и др.) и не имеют повреждений",
          "complies": 1,
          "does_not_comply": null,
          "comment": ""
        },
        {
          "number": 2,
          "description": "Все отходы собираются раздельно.",
          "complies": 0,
          "does_not_comply": 0,
          "comment": "В контейнере для пластика обнаружены бумажные отходы"
        },
        {
          "number": 3,
          "description": "Места и стеллажи, предназначенные для хранения сырья, основных и вспомогательных материалов (на участке, кладовых, складах) идентифицированы и в исправном состоянии.",
          "complies": 1,
          "does_not_comply": null,
          "comment": ""
        },
        {
          "number": 4,
          "description": "В маркировочных ярлыках (этикетках) для идентификации изготавливаемой продукции, размещенных на оборудовании в ячейках с надписью «Для маркировочных ярлыков», указана дата, соответствующая дню проведения проверки",
          "complies": 0,
          "does_not_comply": 0,
          "comment": "На станках №2 и №5 обнаружены ярлыки с устаревшей датой"
        },
        {
          "number": 5,
          "description": "Электроштабелеры, гидротележеки размещены в установленных местах, идентифицированы наименованием участка и имеют отметку о последних испытаниях",
          "complies": 1,
          "does_not_comply": null,
          "comment": ""
        },
        {
          "number": 6,
          "description": "Место размещения на участке питьевой воды содержится в надлежащем состоянии: бутыль с водой без упаковочных материалов, использованные стаканчики в урне, посторонних предметов на кулере и около него нет, урна не переполнена",
          "complies": 0,
          "does_not_comply": 0,
          "comment": "Урна переполнена использованными стаканчиками"
        }
      ],
      "subdivisions": {}
    }
  }
}